odoo/addons/base_user_signature/README.rst
odoo/addons/base_user_signature/__init__.py
odoo/addons/base_user_signature/__manifest__.py
odoo/addons/base_user_signature/i18n/base_user_signature.pot
odoo/addons/base_user_signature/i18n/fr.po
odoo/addons/base_user_signature/i18n/it.po
odoo/addons/base_user_signature/models/__init__.py
odoo/addons/base_user_signature/models/res_users.py
odoo/addons/base_user_signature/readme/CONTRIBUTORS.md
odoo/addons/base_user_signature/readme/DESCRIPTION.md
odoo/addons/base_user_signature/readme/USAGE.md
odoo/addons/base_user_signature/static/description/icon.png
odoo/addons/base_user_signature/static/description/index.html
odoo/addons/base_user_signature/tests/__init__.py
odoo/addons/base_user_signature/tests/test_base_user_signature.py
odoo/addons/base_user_signature/views/res_users_view.xml
odoo_addon_base_user_signature-17.0.1.0.0.2.dist-info/METADATA
odoo_addon_base_user_signature-17.0.1.0.0.2.dist-info/WHEEL
odoo_addon_base_user_signature-17.0.1.0.0.2.dist-info/top_level.txt
odoo_addon_base_user_signature-17.0.1.0.0.2.dist-info/RECORD
